[{"line":3,"elements":[{"line":5,"name":"User navigates to google website","description":"","type":"background","keyword":"Background","steps":[]},{"start_timestamp":"2022-06-19T07:34:14.726Z","before":[{"result":{"duration":103639000000,"status":"passed"},"match":{"location":"org.example.stepDefinitions.Hooks.openBrowser()"}}],"line":7,"name":"user can search for any item by item's name","description":"","id":"user-could-search-for-any-item;user-can-search-for-any-item-by-item-s-name","after":[{"result":{"duration":10288000000,"status":"passed"},"match":{"location":"org.example.stepDefinitions.Hooks.closeBrowser()"}}],"type":"scenario","keyword":"Scenario","steps":[{"result":{"duration":1611000000,"status":"passed"},"line":8,"name":"user press on search field","match":{"location":"org.example.stepDefinitions.SD01_SearchFunctionality.clickSearchField()"},"keyword":"When "},{"result":{"duration":245000000,"status":"passed"},"line":9,"name":"user search with Item name\"InstaBug\"","match":{"arguments":[{"val":"InstaBug","offset":27}],"location":"org.example.stepDefinitions.SD01_SearchFunctionality.searchWithItemName(java.lang.String)"},"keyword":"And "},{"result":{"duration":23705000000,"status":"passed"},"line":10,"name":"user press on search button","match":{"location":"org.example.stepDefinitions.SD01_SearchFunctionality.clickSearchButton()"},"keyword":"And "},{"result":{"error_message":"java.lang.AssertionError: expected [true] but found [false]\r\n\tat org.testng.Assert.fail(Assert.java:110)\r\n\tat org.testng.Assert.failNotEquals(Assert.java:1413)\r\n\tat org.testng.Assert.assertTrue(Assert.java:56)\r\n\tat org.testng.Assert.assertTrue(Assert.java:66)\r\n\tat org.example.pages.P01_SearchPage.results(P01_SearchPage.java:16)\r\n\tat org.example.stepDefinitions.SD01_SearchFunctionality.find_results(SD01_SearchFunctionality.java:29)\r\n\tat ✽.user could find relative result(file:///E:/New%20folder/E-commerce-App-Automation-Testing-main/InstaBug-Task/TestAutomation_InstaBugTask/src/main/resources/features/SC01_search.feature:11)\r\n","duration":7413000000,"status":"failed"},"line":11,"name":"user could find relative result","match":{"location":"org.example.stepDefinitions.SD01_SearchFunctionality.find_results()"},"keyword":"Then "}],"tags":[{"name":"@smoke"}]}],"name":"User could search for any item","description":"","id":"user-could-search-for-any-item","keyword":"Feature","uri":"file:src/main/resources/features/SC01_search.feature","tags":[{"name":"@smoke","type":"Tag","location":{"line":1,"column":1}}]}]